shoutd/__init__.py
shoutd/shoutd.py
shoutd-0.1.1.data/scripts/shoutd
shoutd-0.1.1.data/scripts/shoutdctl
shoutd-0.1.1.dist-info/DESCRIPTION.rst
shoutd-0.1.1.dist-info/METADATA
shoutd-0.1.1.dist-info/RECORD
shoutd-0.1.1.dist-info/WHEEL
shoutd-0.1.1.dist-info/metadata.json
shoutd-0.1.1.dist-info/top_level.txt
